djenerics
