Metadata-Version: 1.1
Name: djenerics
Version: 1.0.1
Summary: A collection of Django 1.5+ and Django Rest Framework 3.0+ utilities
Home-page: http://nrocco.github.io/
Author: Nico Di Rocco
Author-email: dirocco.nico@gmail.com
License: Copyright (c) 2013, Nico Di Rocco.
